testbench_sardine/__init__.py
testbench_sardine/main.py
testbench_sardine/py.typed
testbench_sardine/utils.py
testbench_sardine-1.0.4.dist-info/METADATA
testbench_sardine-1.0.4.dist-info/WHEEL
testbench_sardine-1.0.4.dist-info/LICENSE
testbench_sardine-1.0.4.dist-info/RECORD
