Metadata-Version: 2.1
Name: testbench-sardine
Version: 1.0.4
Summary: Personal testbench for trying out stuff.
Home-page: https://github.com/trallnag/testbench-sardine
License: MIT
Author: Tim Schwenke
Author-email: tim@trallnag.com
Requires-Python: >=3.10,<4.0
Classifier: License :: OSI Approved :: MIT License
Classifier: Programming Language :: Python :: 3
Classifier: Programming Language :: Python :: 3.10
Classifier: Programming Language :: Python :: 3.11
Requires-Dist: fastapi (>=0.89.1,<0.90.0)
Requires-Dist: requests (>=2.28.2,<3.0.0)
Requires-Dist: uvicorn (>=0.20.0,<0.21.0)
Project-URL: Repository, https://github.com/trallnag/testbench-sardine
